biobalm/__init__.py
biobalm/_pint_reachability.py
biobalm/control.py
biobalm/drivers.py
biobalm/interaction_graph_utils.py
biobalm/petri_net_translation.py
biobalm/space_utils.py
biobalm/succession_diagram.py
biobalm/symbolic_utils.py
biobalm/trappist_core.py
biobalm/types.py
biobalm/_sd_algorithms/__init__.py
biobalm/_sd_algorithms/expand_attractor_seeds.py
biobalm/_sd_algorithms/expand_bfs.py
biobalm/_sd_algorithms/expand_dfs.py
biobalm/_sd_algorithms/expand_minimal_spaces.py
biobalm/_sd_algorithms/expand_source_SCCs.py
biobalm/_sd_algorithms/expand_source_blocks.py
biobalm/_sd_algorithms/expand_to_target.py
biobalm/_sd_attractors/__init__.py
biobalm/_sd_attractors/attractor_candidates.py
biobalm/_sd_attractors/attractor_symbolic.py
biobalm-0.4.3.dist-info/licenses/LICENSE
biobalm-0.4.3.dist-info/METADATA
biobalm-0.4.3.dist-info/WHEEL
biobalm-0.4.3.dist-info/top_level.txt
biobalm-0.4.3.dist-info/RECORD
