Metadata-Version: 2.4
Name: biobalm
Version: 0.4.3
Summary: Boolean Attractor Landscape Mapper
Author-email: Jordan Rozum <jrozum@binghamton.edu>
License: Copyright (c) 2024 Van-Giang Trinh, Kyu Hyong Park, Samuel Pastva, Jordan C Rozum
Requires-Python: >=3.11
License-File: LICENSE
Requires-Dist: biodivine_aeon>=1.2.5
Requires-Dist: clingo>=5.6.2
Requires-Dist: networkx>=2.8.8
Provides-Extra: pint
Requires-Dist: pypint==1.6.2; extra == "pint"
Dynamic: license-file
